optimism/__init__.py
optimism/assets/dispute_game_factory.json
optimism/assets/erc20.json
optimism/assets/fault_dispute_game.json
optimism/assets/l1_cross_messenger.json
optimism/assets/l1_standard_bridge.json
optimism/assets/l2_cross_messenger.json
optimism/assets/l2_output_oracle.json
optimism/assets/l2_standard_bridge.json
optimism/assets/l2_to_l1_message_passer.json
optimism/assets/optimism_erc20.json
optimism/assets/optimism_portal.json
optimism/config.json
optimism/constants.py
optimism/contracts.py
optimism/cross_chain_messenger.py
optimism/types.py
optimism/utils.py
optimism_python-0.3.1.dist-info/LICENSE
optimism_python-0.3.1.dist-info/WHEEL
optimism_python-0.3.1.dist-info/METADATA
optimism_python-0.3.1.dist-info/RECORD
